leakpro/.gitignore
leakpro/LICENSE
leakpro/__main__.py
leakpro/config.py
leakpro/environment.yml
leakpro/model.py
leakpro/requirements.txt
leakpro/third_party.txt
leakpro/attacks/attack_scheduler.py
leakpro/attacks/mia_attacks/abstract_mia.py
leakpro/attacks/mia_attacks/attack_factory_mia.py
leakpro/attacks/mia_attacks/attack_p.py
leakpro/attacks/mia_attacks/lira.py
leakpro/attacks/mia_attacks/qmia.py
leakpro/attacks/mia_attacks/rmia.py
leakpro/attacks/utils/distillation_model_handler.py
leakpro/attacks/utils/model_handler.py
leakpro/attacks/utils/shadow_model_handler.py
leakpro/attacks/utils/threshold_computation.py
leakpro/config/moreno_audit.yaml
leakpro/metrics/attack_result.py
leakpro/reporting/utils.py
leakpro/signals/signal.py
leakpro/user_inputs/abstract_input_handler.py
leakpro/user_inputs/moreno_input_handler.py
leakpro/utils/extract_true_positives.py
leakpro/utils/input_handler.py
moreno/__main__.py
moreno/cli.py
moreno/config.py
moreno/custom_representation.py
moreno/data/ames.csv
moreno/data/ames.tab
moreno/data/bbb.csv
moreno/data/bbb_martins.tab
moreno/data/del.csv
moreno/data/herg.csv
moreno/data/herg_central.tab
moreno/data/seq2seq_train.csv
moreno/data/seq2seq_validation.csv
moreno/data_modules/custom_datamodule.py
moreno/data_modules/datasets_and_collate_functions.py
moreno/data_modules/download_and_clean_data.py
moreno/data_modules/preinstalled_datamodule.py
moreno/data_modules/user_datamodule.py
moreno/factories/datasets.py
moreno/factories/models.py
moreno/hyperparameter_optimizers/CNN_optimizer.py
moreno/hyperparameter_optimizers/MLP_optimizer.py
moreno/hyperparameter_optimizers/MPNN_optimizer.py
moreno/hyperparameter_optimizers/optimizer.py
moreno/models/CNN.py
moreno/models/MLP.py
moreno/models/MPNN.py
moreno/utils/clean_data.py
moreno/utils/convert_representations.py
moreno/utils/csv_file_operations.py
moreno/utils/plot_roc.py
moreno/utils/predict.py
moreno_encoders/__main__.py
moreno_encoders/datamodules/seq2seq.py
molprivacy-0.1.1.dist-info/METADATA
molprivacy-0.1.1.dist-info/WHEEL
molprivacy-0.1.1.dist-info/entry_points.txt
molprivacy-0.1.1.dist-info/licenses/LICENSE
molprivacy-0.1.1.dist-info/RECORD
