Metadata-Version: 2.4
Name: molprivacy
Version: 0.1.1
Summary: Assessing training data privacy for molecular property prediction.
Project-URL: Homepage, https://github.com/FabianKruger/molprivacy
Project-URL: Issues, https://github.com/FabianKruger/molprivacy/issues
Author-email: Fabian Krueger <fabian.kruger@astrazeneca.com>
License: MIT License
License-File: LICENSE
Keywords: MIA,cheminformatics,membership inference attack,neural networks,privacy
Classifier: License :: OSI Approved :: MIT License
Classifier: Operating System :: OS Independent
Classifier: Programming Language :: Python :: 3.12
Requires-Python: >=3.12
Requires-Dist: chemprop==1.6.1
Requires-Dist: joblib==1.4.2
Requires-Dist: lightning==2.4.0
Requires-Dist: matplotlib==3.8.4
Requires-Dist: numpy==1.26.4
Requires-Dist: optuna-integration==4.0.0
Requires-Dist: optuna==3.6.1
Requires-Dist: pandas==2.2.3
Requires-Dist: pyyaml==6.0.2
Requires-Dist: rdkit==2024.3.2
Requires-Dist: scikit-learn==1.5.2
Requires-Dist: scipy==1.14.1
Requires-Dist: seaborn==0.13.2
Requires-Dist: torch==2.4.0
Requires-Dist: tqdm==4.66.5
